SomeRandomAPI/SomeRandomAPI.py
SomeRandomAPI/__init__.py
SomeRandomAPI-0.0.6.dist-info/LICENSE.txt
SomeRandomAPI-0.0.6.dist-info/METADATA
SomeRandomAPI-0.0.6.dist-info/WHEEL
SomeRandomAPI-0.0.6.dist-info/top_level.txt
SomeRandomAPI-0.0.6.dist-info/RECORD
