Metadata-Version: 2.1
Name: SomeRandomAPI
Version: 0.0.6
Summary: A wrapper library for some-random-api.
Home-page: https://bruhdev.com
Author: BruhDev
Author-email: mr.bruh.dev@gmail.com
License: UNKNOWN
Platform: UNKNOWN
Requires-Python: >=3.7
